pdf_diff/__init__.py
pdf_diff/command_line.py
pdf_diff-0.9.1.dist-info/LICENSE
pdf_diff-0.9.1.dist-info/METADATA
pdf_diff-0.9.1.dist-info/WHEEL
pdf_diff-0.9.1.dist-info/entry_points.txt
pdf_diff-0.9.1.dist-info/top_level.txt
pdf_diff-0.9.1.dist-info/RECORD
