Metadata-Version: 2.1
Name: pdf-diff
Version: 0.9.1
Summary: Finds differences between two PDF documents
Home-page: https://github.com/JoshData/pdf-diff
Author: Joshua Tauberer
Author-email: jt@occams.info
License: CC0 1.0 Universal
Platform: UNKNOWN
Requires-Dist: diff-match-patch-python
Requires-Dist: lxml
Requires-Dist: pillow
